.DS_Store
gDNS-0.1.4.dist-info/DESCRIPTION.rst
gDNS-0.1.4.dist-info/METADATA
gDNS-0.1.4.dist-info/RECORD
gDNS-0.1.4.dist-info/WHEEL
gDNS-0.1.4.dist-info/entry_points.txt
gDNS-0.1.4.dist-info/metadata.json
gDNS-0.1.4.dist-info/top_level.txt
gdns/__init__.py
gdns/main.py
gdns/patches.py
gdns/rr.py
