Metadata-Version: 2.0
Name: gDNS
Version: 0.1.4
Summary: Google DNS-over-HTTPS
Home-page: https://github.com/arn7av/gDNS
Author: arnAV
Author-email: arnav@arnav.at
License: UNKNOWN
Download-URL: https://github.com/arn7av/gDNS/archive/0.1.4.tar.gz
Keywords: dns https google gdns
Platform: UNKNOWN
Classifier: Development Status :: 4 - Beta
Classifier: Intended Audience :: End Users/Desktop
Classifier: Topic :: Internet :: Name Service (DNS)
Classifier: License :: OSI Approved :: MIT License
Classifier: Programming Language :: Python :: 2
Classifier: Programming Language :: Python :: 2.7
Classifier: Programming Language :: Python :: 3
Classifier: Programming Language :: Python :: 3.3
Classifier: Programming Language :: Python :: 3.4
Classifier: Programming Language :: Python :: 3.5
Classifier: Programming Language :: Python :: 3.6
Classifier: Programming Language :: Python :: 3.7
Classifier: Framework :: Twisted
Requires-Python: >=2.7, !=3.0.*, !=3.1.*, !=3.2.*, <4
Requires-Dist: Twisted
Requires-Dist: tornado
Requires-Dist: requests
Requires-Dist: requests-toolbelt
